ghrocker/__init__.py
ghrocker/ghpages_extension.py
ghrocker/ghrocker.py
ghrocker/templates/ghpages_snippet.Dockerfile.em
ghrocker-0.0.10.dist-info/licenses/LICENSE
ghrocker-0.0.10.dist-info/METADATA
ghrocker-0.0.10.dist-info/WHEEL
ghrocker-0.0.10.dist-info/entry_points.txt
ghrocker-0.0.10.dist-info/top_level.txt
ghrocker-0.0.10.dist-info/RECORD
