Metadata-Version: 2.4
Name: ghrocker
Version: 0.0.10
Summary: A rocker extension to locally test github pages.
Author-email: Tully Foote <tfoote@osrfoundation.org>
License: Apache 2.0
Project-URL: Homepage, https://github.com/tfoote/ghrocker
Classifier: Programming Language :: Python :: 3
Classifier: License :: OSI Approved :: Apache Software License
Classifier: Operating System :: OS Independent
Requires-Python: >=3.6
License-File: LICENSE
Requires-Dist: empy
Requires-Dist: rocker>=0.2.13
Dynamic: license-file
